MANIFEST.in
README.md
setup.py
simpleValidator.egg-info/PKG-INFO
simpleValidator.egg-info/SOURCES.txt
simpleValidator.egg-info/dependency_links.txt
simpleValidator.egg-info/top_level.txt
simplevalidator/.DS_Store
simplevalidator/__init__.py
simplevalidator/__init__.pyc
simplevalidator/i18n.py
simplevalidator/i18n.pyc
simplevalidator/rules.py
simplevalidator/rules.pyc
simplevalidator/settings.py
simplevalidator/settings.pyc
simplevalidator/__pycache__/.DS_Store
simplevalidator/__pycache__/__init__.cpython-33.pyc
simplevalidator/__pycache__/i18n.cpython-33.pyc
simplevalidator/__pycache__/rules.cpython-33.pyc
simplevalidator/__pycache__/settings.cpython-33.pyc
simplevalidator/lang/.DS_Store
simplevalidator/lang/en/.DS_Store
simplevalidator/lang/en/LC_MESSAGES/simpleValidator.mo
simplevalidator/lang/en/LC_MESSAGES/simpleValidator.po
simplevalidator/lang/fr/.DS_Store
simplevalidator/lang/fr/LC_MESSAGES/simpleValidator.mo
simplevalidator/lang/fr/LC_MESSAGES/simpleValidator.po
simplevalidator/lang/ja/.DS_Store
simplevalidator/lang/ja/LC_MESSAGES/simpleValidator.mo
simplevalidator/lang/ja/LC_MESSAGES/simpleValidator.po