Metadata-Version: 1.1
Name: simpleValidator
Version: 0.0.6.0
Summary: A small, extensible python library to deal with web validations !
Home-page: https://github.com/markleent/simpleValidator.git
Author: Ken Martel
Author-email: ashes.dust@gmail.com
License: MIT
Platform: UNKNOWN
Classifier: Development Status :: 3 - Alpha
Classifier: Intended Audience :: Developers
Classifier: License :: OSI Approved :: MIT License
Classifier: Operating System :: POSIX
Classifier: Programming Language :: Python
Classifier: Topic :: Software Development :: Libraries :: Python Modules
Classifier: Topic :: Utilities
